python_qtpip-0.3.0.data/data/share/opensesame_extensions/package_manager/info.yaml
python_qtpip-0.3.0.data/data/share/opensesame_extensions/package_manager/package_manager.py
qtpip/__init__.py
qtpip/__main__.py
qtpip/_package.py
qtpip/_packagemanager.py
qtpip/_qpackagematrix.py
qtpip/_qpipwidget.py
qtpip/contextmenu.py
qtpip/decorators.py
qtpip/utils.py
qtpip/data/pipwidget.ui
python_qtpip-0.3.0.dist-info/COPYING
python_qtpip-0.3.0.dist-info/METADATA
python_qtpip-0.3.0.dist-info/WHEEL
python_qtpip-0.3.0.dist-info/entry_points.txt
python_qtpip-0.3.0.dist-info/top_level.txt
python_qtpip-0.3.0.dist-info/RECORD
