Metadata-Version: 2.1
Name: python-qtpip
Version: 0.3.0
Summary: A graphical manager for PyPi plus an OpenSesame extension
Home-page: https://github.com/smathot/python-qtpip
Author: Sebastiaan Mathot
Author-email: s.mathot@cogsci.nl
License: UNKNOWN
Platform: UNKNOWN
Classifier: Intended Audience :: Science/Research
Classifier: Topic :: Scientific/Engineering
Classifier: Environment :: MacOS X
Classifier: Environment :: Win32 (MS Windows)
Classifier: Environment :: X11 Applications
Classifier: License :: OSI Approved :: Apache Software License
Classifier: Programming Language :: Python :: 3
Requires-Dist: yolk3k
Requires-Dist: python-qdatamatrix
